sacc/__init__.py
sacc/covariance.py
sacc/data_types.py
sacc/io.py
sacc/sacc.py
sacc/utils.py
sacc/windows.py
sacc/tracer_uncertainty/__init__.py
sacc/tracer_uncertainty/base.py
sacc/tracer_uncertainty/nz.py
sacc/tracers/__init__.py
sacc/tracers/base.py
sacc/tracers/clusters.py
sacc/tracers/maps.py
sacc/tracers/misc.py
sacc/tracers/nz.py
sacc/tracers/survey.py
sacc-2.1.dist-info/licenses/LICENSE
sacc-2.1.dist-info/METADATA
sacc-2.1.dist-info/WHEEL
sacc-2.1.dist-info/top_level.txt
sacc-2.1.dist-info/RECORD
