Metadata-Version: 2.4
Name: sacc
Version: 2.1
Summary: SACC - the LSST/DESC summary statistic data format library
Author-email: LSST DESC <joezuntz@googlemail.com>
License: BSD-3-Clause
Project-URL: Homepage, https://github.com/LSSTDESC/sacc
Classifier: Programming Language :: Python :: 3
Classifier: Operating System :: OS Independent
License-File: LICENSE
Requires-Dist: scipy
Requires-Dist: numpy>=2
Requires-Dist: astropy
Provides-Extra: all
Requires-Dist: qp-prob[all]>=1; extra == "all"
Requires-Dist: numpydoc; extra == "all"
Provides-Extra: doc
Requires-Dist: numpydoc; extra == "doc"
Provides-Extra: qp
Requires-Dist: qp-prob[all]>=1; extra == "qp"
Dynamic: license-file
